{
    "version": "2.0.1.19",
    "homepage": "https://github.com/PixiEditor/PixiEditor",
    "license": "LGPL-3.0",
    "description": "The only 2D Graphics Editor you'll ever need",
    "architecture": {
        "64bit": {
            "url": "https://github.com/PixiEditor/PixiEditor/releases/download/2.0.1.19/PixiEditor.2.0.1.19.x64-win.zip",
            "hash": "96e7ce4f96e9e1474f4b7712763e49d290c71176be15f33d498c08ea6f482791"
        }
    },
    "extract_to": "",
    "shortcuts": [
        [
            "PixiEditor/PixiEditor.exe",
            "pixi"
        ]
    ],
    "checkver": {
        "github": "https://github.com/PixiEditor/PixiEditor"
    },
    "autoupdate": {
        "architecture": {
            "64bit": {
                "url": "https://github.com/PixiEditor/PixiEditor/releases/download/$version/PixiEditor.$version.x64-win.zip"
            }
        }
    }
}
